abricot/__init__.py
abricot/abr_path/__init__.py
abricot/abr_path/transform.py
abricot/abr_random/__init__.py
abricot/abr_random/abr_string.py
abricot/abr_thread/__init__.py
abricot/abr_thread/daemon.py
abricot-0.0.5a2.dist-info/LICENSE
abricot-0.0.5a2.dist-info/METADATA
abricot-0.0.5a2.dist-info/WHEEL
abricot-0.0.5a2.dist-info/top_level.txt
abricot-0.0.5a2.dist-info/RECORD
