Metadata-Version: 2.1
Name: abricot
Version: 0.0.5a2
Summary: ...
Author-email: TENG CHIH HENG <wiiiy5505aa@gmail.com>
Project-URL: Homepage, https://github.com/henry202-TENG/abricot
Requires-Python: >=3.7
License-File: LICENSE
